k3cloud_webapi_sdk/__init__.py
k3cloud_webapi_sdk/main.py
k3cloud_webapi_sdk/sample.py
k3cloud_webapi_sdk/const/__init__.py
k3cloud_webapi_sdk/const/const_define.py
k3cloud_webapi_sdk/const/header_param.py
k3cloud_webapi_sdk/core/__init__.py
k3cloud_webapi_sdk/core/webapi_client.py
k3cloud_webapi_sdk/model/__init__.py
k3cloud_webapi_sdk/model/api_config.py
k3cloud_webapi_sdk/model/cookie.py
k3cloud_webapi_sdk/model/cookie_store.py
k3cloud_webapi_sdk/model/identity.py
k3cloud_webapi_sdk/model/query_param.py
k3cloud_webapi_sdk/util/__init__.py
k3cloud_webapi_sdk/util/base64_util.py
k3cloud_webapi_sdk/util/config_util.py
k3cloud_webapi_sdk/util/encode_util.py
k3cloud_webapi_sdk/util/hmac_util.py
rdcrm/__init__.py
rdcrm/customer.py
rdcrm/login.py
rdcrm/product.py
rdcrm/salesOrder.py
rdcrm/bill/__init__.py
rdcrm/bill/salesOrder.py
rdcrm/md/__init__.py
rdcrm/md/customer.py
rdcrm/md/product.py
rderp/__init__.py
rderp/main.py
rderp/bill/__init__.py
rderp/md/__init__.py
rderp/md/material.py
k3cloud_webapi_sdk-3.0.3.dist-info/LICENSE
k3cloud_webapi_sdk-3.0.3.dist-info/METADATA
k3cloud_webapi_sdk-3.0.3.dist-info/WHEEL
k3cloud_webapi_sdk-3.0.3.dist-info/top_level.txt
k3cloud_webapi_sdk-3.0.3.dist-info/RECORD
