Metadata-Version: 2.1
Name: k3cloud-webapi-sdk
Version: 3.0.3
Summary: erp web api in py language 
Home-page: http://www.reshapedata.com
Author: hulilei
Author-email: hulilei@takewiki.com.cn
License: Apache License
Keywords: reshapedata,k3cloud_webapi_sdk
Platform: UNKNOWN
Requires-Python: >=3.6
License-File: LICENSE
Requires-Dist: requests
